django_auth0_user/__init__.py
django_auth0_user/admin.py
django_auth0_user/apps.py
django_auth0_user/backend.py
django_auth0_user/clean.py
django_auth0_user/management/__init__.py
django_auth0_user/management/commands/__init__.py
django_auth0_user/management/commands/create_auth0_rule_configs.py
django_auth0_user/management/commands/create_auth0_rules.py
django_auth0_user/management/commands/delete_auth0_rule_configs.py
django_auth0_user/management/commands/delete_auth0_rules.py
django_auth0_user/management/commands/enable_superuser.py
django_auth0_user/migrations/__init__.py
django_auth0_user/models.py
django_auth0_user/permission_checks.py
django_auth0_user/rest_framework/__init__.py
django_auth0_user/rest_framework/authentication.py
django_auth0_user/settings.py
django_auth0_user/templatetags/__init__.py
django_auth0_user/templatetags/auth0.py
django_auth0_user/util/__init__.py
django_auth0_user/util/auth0_api.py
django_auth0_user/validators.py
django_auth0_user-0.16.5.dist-info/LICENSE
django_auth0_user-0.16.5.dist-info/WHEEL
django_auth0_user-0.16.5.dist-info/METADATA
django_auth0_user-0.16.5.dist-info/RECORD
